vandal/__init__.py
vandal/core.py
vandal/demo_vandal.py
vandal/playwright_ext.py
project_vandal-0.2.0.dist-info/METADATA
project_vandal-0.2.0.dist-info/WHEEL
project_vandal-0.2.0.dist-info/top_level.txt
project_vandal-0.2.0.dist-info/RECORD
