Metadata-Version: 2.4
Name: project-vandal
Version: 0.2.0
Summary: A deterministic UI mutation testing engine for Playwright
Author-email: Dhiraj Das <dhirajdas.666@gmail.com>
Project-URL: Homepage, https://github.com/godhiraj-code/vandal
Project-URL: Bug Tracker, https://github.com/godhiraj-code/vandal/issues
Project-URL: Author Website, https://www.dhirajdas.dev
Classifier: Programming Language :: Python :: 3
Classifier: License :: OSI Approved :: MIT License
Classifier: Operating System :: OS Independent
Classifier: Topic :: Software Development :: Testing
Requires-Python: >=3.8
Requires-Dist: playwright>=1.30.0
